loko/__init__.py
loko/cli_types.py
loko/config.py
loko/generator.py
loko/runner.py
loko/utils.py
loko/validators.py
loko/cli/__init__.py
loko/cli/commands/__init__.py
loko/cli/commands/completion.py
loko/cli/commands/config.py
loko/cli/commands/control.py
loko/cli/commands/lifecycle.py
loko/cli/commands/registry.py
loko/cli/commands/secrets.py
loko/cli/commands/status.py
loko/cli/commands/utility.py
loko/cli/commands/workloads.py
loko/templates/loko.yaml.example
loko/templates/traefik-tcp-routes.yaml.j2
loko/templates/workload_presets.yaml
loko/templates/containerd/hosts.toml.j2
loko/templates/dnsmasq/config.conf.j2
loko/templates/helmfile/helmfile.yaml.j2
loko/templates/kind/cluster.yaml.j2
loko/templates/test-app/Dockerfile
loko/templates/test-app/ep.sh
loko/templates/test-app/manifest.yaml.j2
loko/updates/__init__.py
loko/updates/fetchers.py
loko/updates/parsers.py
loko/updates/upgrader.py
loko/updates/yaml_walker.py
loko_k8s-0.1.2.dist-info/METADATA
loko_k8s-0.1.2.dist-info/WHEEL
loko_k8s-0.1.2.dist-info/entry_points.txt
loko_k8s-0.1.2.dist-info/licenses/LICENSE
loko_k8s-0.1.2.dist-info/RECORD
