Metadata-Version: 2.4
Name: loko-k8s
Version: 0.1.2
Summary: Local Kubernetes Environment Manager - Simplified local K8s development with Kind
Project-URL: Homepage, https://github.com/bojanraic/loko
Project-URL: Repository, https://github.com/bojanraic/loko
Project-URL: Issues, https://github.com/bojanraic/loko/issues
Author-email: Bojan Raic <code+loko@bojan.io>
License: MIT
License-File: LICENSE
Keywords: containers,development,devops,k8s,kind,kubernetes,local
Classifier: Development Status :: 4 - Beta
Classifier: Intended Audience :: Developers
Classifier: License :: OSI Approved :: MIT License
Classifier: Programming Language :: Python :: 3
Classifier: Programming Language :: Python :: 3.9
Classifier: Programming Language :: Python :: 3.10
Classifier: Programming Language :: Python :: 3.11
Classifier: Programming Language :: Python :: 3.12
Classifier: Programming Language :: Python :: 3.13
Classifier: Programming Language :: Python :: 3.14
Classifier: Topic :: Software Development :: Build Tools
Classifier: Topic :: System :: Systems Administration
Requires-Python: >=3.9
Requires-Dist: jinja2>=3.1.0
Requires-Dist: packaging>=21.0
Requires-Dist: pydantic>=2.0.0
Requires-Dist: pyyaml>=6.0
Requires-Dist: rich>=13.0.0
Requires-Dist: ruamel-yaml>=0.17.0
Requires-Dist: shellingham>=1.5.0
Requires-Dist: typer>=0.9.0
Provides-Extra: test
Requires-Dist: pytest-cov>=4.0.0; extra == 'test'
Requires-Dist: pytest>=7.0.0; extra == 'test'
